meilisearch_tui/__init__.py
meilisearch_tui/__main__.py
meilisearch_tui/client.py
meilisearch_tui/config.py
meilisearch_tui/errors.py
meilisearch_tui/main.py
meilisearch_tui/meilisearch.css
meilisearch_tui/py.typed
meilisearch_tui/screens/__init__.py
meilisearch_tui/screens/configuration.py
meilisearch_tui/screens/indexes.py
meilisearch_tui/screens/search.py
meilisearch_tui/utils.py
meilisearch_tui/widgets/__init__.py
meilisearch_tui/widgets/index.py
meilisearch_tui/widgets/index_sidebar.py
meilisearch_tui/widgets/input.py
meilisearch_tui/widgets/messages.py
meilisearch_tui-0.9.1.dist-info/LICENSE
meilisearch_tui-0.9.1.dist-info/METADATA
meilisearch_tui-0.9.1.dist-info/WHEEL
meilisearch_tui-0.9.1.dist-info/entry_points.txt
meilisearch_tui-0.9.1.dist-info/RECORD
