Metadata-Version: 2.3
Name: meilisearch-tui
Version: 0.9.1
Summary: A TUI for Managing and Searching with Meilisearch
License: MIT
Keywords: meilisearch,tui
Author: Paul Sanders
Author-email: psanders1@gmail.com
Requires-Python: >=3.8,<4.0
Classifier: Development Status :: 7 - Inactive
Classifier: License :: OSI Approved :: MIT License
Classifier: Operating System :: OS Independent
Classifier: Programming Language :: Python :: 3
Classifier: Programming Language :: Python :: 3.8
Classifier: Programming Language :: Python :: 3.9
Classifier: Programming Language :: Python :: 3.10
Classifier: Programming Language :: Python :: 3.11
Classifier: Programming Language :: Python :: 3.12
Classifier: Programming Language :: Python :: 3.13
Requires-Dist: meilisearch-python-sdk (==2.12.1)
Requires-Dist: textual (==0.47.1)
Requires-Dist: typer (==0.16.1)
Requires-Dist: uvloop (==0.21.0) ; sys_platform != "win32"
Project-URL: Documentation, https://github.com/sanders41/meilisearch-tui
Project-URL: Homepage, https://github.com/sanders41/meilisearch-tui
Project-URL: Repository, https://github.com/sanders41/meilisearch-tui
